LICENSE
README.md
setup.py
yandex_connect/__init__.py
yandex_connect/base.py
yandex_connect/directory.py
yandex_connect.egg-info/PKG-INFO
yandex_connect.egg-info/SOURCES.txt
yandex_connect.egg-info/dependency_links.txt
yandex_connect.egg-info/not-zip-safe
yandex_connect.egg-info/requires.txt
yandex_connect.egg-info/top_level.txt