Metadata-Version: 2.1
Name: yandex-connect
Version: 0.29b0
Summary: API Yandex Connect
Home-page: http://github.com/zt50tz/yandex-connect
Author: Alexeev Nick
Author-email: n@akolka.ru
License: MIT
Platform: UNKNOWN
